[
    { "begriff": "Abduktion",            "erklaerung": "Schluss von einem beobachteten Ergebnis auf die wahrscheinlichste Ursache." },
    { "begriff": "A‑priori",            "erklaerung": "Erkenntnisse oder Prinzipien, die unabhängig von Erfahrung gelten." },
    { "begriff": "A‑posteriori",        "erklaerung": "Erkenntnisse, die erst durch Erfahrung gewonnen werden." },
    { "begriff": "Absolut",             "erklaerung": "Dasjenige, das ohne Bedingungen und Einschränkungen existiert." },
    { "begriff": "Abstrakt",            "erklaerung": "Nur im Denken existierende, nicht sinnlich Wahrnehmbare Entität." },
    { "begriff": "Agens",               "erklaerung": "Handelnde Instanz; die Fähigkeit des Subjekts, zu handeln." },
    { "begriff": "Analogie",            "erklaerung": "Schlussfolgerung aufgrund von Ähnlichkeiten zwischen zwei Bereichen." },
    { "begriff": "Antinomie",           "erklaerung": "Widerspruch zwischen zwei gleichermaßen begründeten Aussagen." },
    { "begriff": "Ästhetik",            "erklaerung": "Lehre vom Schönen und dem ästhetischen Empfinden." },
    { "begriff": "Autonomie",           "erklaerung": "Fähigkeit zum Selbstbestimmtsein ohne äußere Zwänge." },
    { "begriff": "Bewusstsein",         "erklaerung": "Subjektives Erleben und Gewahrsein geistiger Zustände." },
    { "begriff": "Deduktion",           "erklaerung": "Schluss vom Allgemeinen auf das Besondere." },
    { "begriff": "Determinismus",       "erklaerung": "Lehre, dass alle Ereignisse ursächlich festgelegt sind." },
    { "begriff": "Dialektik",           "erklaerung": "Methode des Erkenntnisgewinns durch Widerspruch und These‑Antithese." },
    { "begriff": "Empirie",             "erklaerung": "Gewinnung von Wissen durch sinnliche Erfahrung." },
    { "begriff": "Empirismus",          "erklaerung": "Erkenntnistheorie, die Erfahrung als einzige Wissensquelle sieht." },
    { "begriff": "Epistemologie",       "erklaerung": "Lehre vom Wissen: Bedingungen, Quellen und Rechtfertigung." },
    { "begriff": "Ethik",               "erklaerung": "Philosophische Reflexion über Moral, Normen und Werte." },
    { "begriff": "Essenz",              "erklaerung": "Wesenhafte Merkmale, die ein Ding zu dem machen, was es ist." },
    { "begriff": "Existenz",            "erklaerung": "Das Sein und Vorhandensein von Dingen oder Subjekten." },
    { "begriff": "Existenziell",        "erklaerung": "Das Mensch‑Sein und die Bedingung der Endlichkeit betreffend." },
    { "begriff": "Freiheit",            "erklaerung": "Möglichkeit zur selbstbestimmten Wahl und Handlung." },
    { "begriff": "Gerechtigkeit",       "erklaerung": "Prinzip der fairen Verteilung von Rechten und Pflichten." },
    { "begriff": "Hermeneutik",         "erklaerung": "Lehre der Interpretation von Texten und Sinnzusammenhängen." },
    { "begriff": "Idealismus",          "erklaerung": "Leugnung der Außenwelt zu Gunsten geistiger Ideen." },
    { "begriff": "Induktion",           "erklaerung": "Schluss vom Besonderen auf das Allgemeine." },
    { "begriff": "Intention",           "erklaerung": "Absicht oder Zielsetzung eines Handelns." },
    { "begriff": "Kausalität",          "erklaerung": "Beziehung von Ursache und Wirkung." },
    { "begriff": "Kognitivismus",       "erklaerung": "Betonung der Rolle mentaler Prozesse beim Erkennen." },
    { "begriff": "Konstruktivismus",    "erklaerung": "Lehre, dass Wissen aktiv vom Subjekt aufgebaut wird." },
    { "begriff": "Kritik",              "erklaerung": "Systematische Überprüfung und Bewertung von Argumenten." },
    { "begriff": "Leib‑Seele‑Problem",   "erklaerung": "Frage nach dem Verhältnis von Körper und Geist." },
    { "begriff": "Logik",               "erklaerung": "Lehre von gültigem Schlussfolgern und Argumentieren." },
        { "begriff": "Aion",                     "erklaerung": "Ewigkeit oder zeitlose Dimension jenseits des chronos." },
        { "begriff": "Akrasia",                 "erklaerung": "Zustand, in dem jemand gegen besseres Wissen handelt." },
        { "begriff": "Aletheia",                "erklaerung": "Wahrheit im Sinne des Entbergens und Offenbarens." },
        { "begriff": "Anomie",                  "erklaerung": "Gesellschaftlicher Zustand der Normlosigkeit." },
        { "begriff": "Aporie",                  "erklaerung": "Unauflösbares philosophisches Problem oder Widerspruch." },
        { "begriff": "Arché",                   "erklaerung": "Ursprung oder Urstoff aller Dinge in der Vorsokratik." },
        { "begriff": "Archetyp",                "erklaerung": "Urbild oder Urform eines Begriffs im Platonismus." },
        { "begriff": "Augmentation",            "erklaerung": "Erweiterung eines Begriffs durch Hinzufügen weiterer Merkmale." },
        { "begriff": "Begriff",                 "erklaerung": "Abstrakte gedankliche Einheit für eine Klasse von Dingen." },
        { "begriff": "Begreifen",               "erklaerung": "Erfassen eines Gegenstandes im Denken." },
        { "begriff": "Binarität",               "erklaerung": "Duale Gegenüberstellung von Begriffen oder Prinzipien." },
        { "begriff": "Bracketing",              "erklaerung": "Phänomenologische Epoché, Ausklammern der natürlichen Einstellung." },
        { "begriff": "Category mistake",        "erklaerung": "Fehlerhafte Zuordnung auf einer falschen Abstraktionsstufe." },
        { "begriff": "Chora",                   "erklaerung": "Platonischer Raum, der Bewegungs- und Formträger ist." },
        { "begriff": "Coherence theory",        "erklaerung": "Wahrheitstheorie, die Kohärenz innerhalb eines Systems betont." },
        { "begriff": "Conatus",                 "erklaerung": "Streben eines Wesens nach Selbsterhaltung (Spinoza)." },
        { "begriff": "Conditional",             "erklaerung": "Bedingter Aussagetyp in der Logik (Wenn-Dann-Struktur)." },
        { "begriff": "Constitutive rule",       "erklaerung": "Regel, die ein Handeln oder Spiel erst möglich macht." },
        { "begriff": "Contextualism",           "erklaerung": "Lehre, dass Bedeutung und Wahrheit vom Kontext abhängen." },
        { "begriff": "Continuum",               "erklaerung": "Ununterbrochene Folge von Werten ohne klare Trennung." },
        { "begriff": "Deontologie",             "erklaerung": "Pflichtethik, die Handlungen nach Regeln beurteilt." },
        { "begriff": "Dialekt",                 "erklaerung": "Gegenüberstellung von Begriffspaaren im philosophischen Diskurs." },
        { "begriff": "Differenz",               "erklaerung": "Unterscheidung als grundsätzliche epistemische Kategorie." },
        { "begriff": "Disjunktion",             "erklaerung": "Logische Oder-Verknüpfung zweier Aussagen." },
        { "begriff": "Doxa",                    "erklaerung": "Meinung oder Glauben im Gegensatz zur Episteme (Wissen)." },
        { "begriff": "Eidos",                   "erklaerung": "Platonische Idee oder Form als wahres Sein." },
        { "begriff": "Ekpyrosis",               "erklaerung": "Stoische Lehre vom zyklischen Weltbrand." },
        { "begriff": "Eleatische Schule",       "erklaerung": "Philosophenschule, die Einheit und Unveränderlichkeit des Seins betonte." },
        { "begriff": "Elision",                 "erklaerung": "Auslassung in Argumenten, die zu Fehlschlüssen führen kann." },
        { "begriff": "Emergenz",                "erklaerung": "Auftreten neuer Eigenschaften auf höheren Komplexitätsebenen." },
        { "begriff": "Entelechie",              "erklaerung": "Aktualität einer potentiellen Form (Aristoteles)." },
        { "begriff": "Ephemer",                 "erklaerung": "Vergänglichkeit und Unbeständigkeit aller Dinge." },
        { "begriff": "Epistemische Gerechtigkeit", "erklaerung": "Faire Berücksichtigung aller Stimmen im Erkenntnisprozess." },
        { "begriff": "Ether",                   "erklaerung": "Aristotelisches Substrat aller Bewegung und Lichtausbreitung." },
        { "begriff": "Euler-Lagrange-Gleichung", "erklaerung": "Variationsprinzip in der mathematischen Physik." },
        { "begriff": "Existential quantifier",  "erklaerung": "Logisches Zeichen ∃, das Existenz aussagt." },
        { "begriff": "Fallibilismus",           "erklaerung": "Erkenntnistheorie, die Irrtum immer zulässt." },
        { "begriff": "Falsifikationismus",      "erklaerung": "Popper’sche Wissenschaftstheorie: Widerlegbarkeit als Kriterium." },
        { "begriff": "Finite",                  "erklaerung": "Endlicher Umfang ohne Unendlichkeit." },
        { "begriff": "Formalismus",             "erklaerung": "Lehre, die die Form von Aussagen betont und den Inhalt temporär ausklammert." },
        { "begriff": "Frame",                   "erklaerung": "Kognitive Struktur, die Erfahrung ordnet." },
        { "begriff": "Fregescher Begriffsschrift", "erklaerung": "Logische Sprache zur Darstellung mathematischer Aussagen." },
        { "begriff": "Generischer Begriff",     "erklaerung": "Allgemeinbezeichnung für eine Klasse von Gegenständen." },
        { "begriff": "Gleichursache",          "erklaerung": "Mehrere Ursachen, die zu demselben Effekt führen." },
        { "begriff": "Hermetizität",            "erklaerung": "Abgeschlossenheit eines Systems gegenüber äußeren Einflüssen." },
        { "begriff": "Heuristik",               "erklaerung": "Verkürztes Verfahren zum Finden von Lösungen." },
        { "begriff": "Holon",                   "erklaerung": "Einheit, die zugleich Teil eines größeren Ganzen ist." },
        { "begriff": "Hylozoismus",            "erklaerung": "Lehre, dass alles Lebendige ist." },
        { "begriff": "Idealtypus",             "erklaerung": "Maximales Modellmerkmal zu Vergleichszwecken (Weber)." },
        { "begriff": "Immanenz",                "erklaerung": "Inhaftieren von Wirklichkeit innerhalb der Welt." },
        { "begriff": "Inferenz",                "erklaerung": "Schlussfolgerung von Prämissen auf Konklusionen." },
        { "begriff": "Inkommensurabilität",     "erklaerung": "Unvergleichbarkeit von Maßstäben oder Theorien." },
        { "begriff": "Intentionalität",         "erklaerung": "Gerichtetheit des Bewusstseins auf Objekte." },
        { "begriff": "Intersubjektivität",      "erklaerung": "Geteilte Bedeutung und Verständigung zwischen Subjekten." },
        { "begriff": "Intransitivität",         "erklaerung": "Nichtübertragbarkeit einer Relation auf eine dritte Instanz." },
        { "begriff": "Isomorphismus",           "erklaerung": "Strukturtreue Abbildung zwischen Systemen." },
        { "begriff": "Judgement",               "erklaerung": "Urteil als Verbindung von Begriffen in der Erkenntnis." },
        { "begriff": "Justizialisierung",       "erklaerung": "Verrechtlichung gesellschaftlicher Konflikte." },
        { "begriff": "Kalenderparadox",         "erklaerung": "Zeitphilosophisches Problem endloser Ketten." },
        { "begriff": "Kategorialgrammatik",     "erklaerung": "Sprachtheorie, die Bedeutung mit syntaktischen Kategorien verknüpft." },
        { "begriff": "Komposition",             "erklaerung": "Zusammenfügung von Elementen zum Ganzen." },
        { "begriff": "Kontrafaktisches Denken",  "erklaerung": "Überlegungen zu Ereignissen, die nicht eingetreten sind." },
        { "begriff": "Kontingenz",              "erklaerung": "Zufälligkeit oder Nicht-Notwendigkeit von Zuständen." },
        { "begriff": "Koyré-Paradoxon",         "erklaerung": "Widerspruch zwischen wissenschaftlicher Theorie und Intuition." },
        { "begriff": "Kriterialismus",          "erklaerung": "Suche nach Kriterien der Wahrheit oder Geltung." },
        { "begriff": "Kybernetik",              "erklaerung": "Lehre von Steuerung und Regelung in Systemen." },
        { "begriff": "Laktanzparadox",          "erklaerung": "Paradoxon der Selbstreferenz in Zeitangaben." },
        { "begriff": "Lebenswelt",              "erklaerung": "Alltägliche Erfahrungswelt (Husserl)." },
        { "begriff": "Legitimität",             "erklaerung": "Anerkennung von Autorität und Rechtmäßigkeit." },
        { "begriff": "Logischer Formismus",      "erklaerung": "Formalistische Ausrichtung der Logik ohne semantische Einbindung." },
        { "begriff": "Machine ethics",          "erklaerung": "Ethik für autonome Systeme und KI." },
        { "begriff": "Mathematische Platonik",  "erklaerung": "Glaube an die Realität abstrakter mathematischer Objekte." },
        { "begriff": "Mehrheitsprinzip",        "erklaerung": "Entscheidungsregel basierend auf Stimmenmehrheit." },
    { "begriff": "Materialismus",       "erklaerung": "Lehre, dass nur materielle Substanz Realität hat." },
    { "begriff": "Metaphysik",          "erklaerung": "Untersuchung der grundsätzlichen Strukturen des Seins." },
    { "begriff": "Monismus",            "erklaerung": "Lehre von der Einheit aller Wirklichkeit." },
    { "begriff": "Nominalismus",        "erklaerung": "Leugnung universaler Begriffe zugunsten individueller Einzelobjekte." },
    { "begriff": "Ontologie",           "erklaerung": "Teilgebiet der Metaphysik, Lehre vom Sein." },
    { "begriff": "Phänomenologie",      "erklaerung": "Beschreibende Analyse von Bewusstseinsinhalten." },
    { "begriff": "Platonismus",         "erklaerung": "Lehre von einer transzendenten Sphäre unveränderlicher Ideen." },
    { "begriff": "Polytheismus",        "erklaerung": "Glaubensform mit mehreren göttlichen Wesen." },
    { "begriff": "Pragmatismus",        "erklaerung": "An Erkenntnissen ist der praktische Erfolg entscheidend." },
    { "begriff": "Prämisse",            "erklaerung": "Vorausgesetzte Aussage in einem Argument." },
    { "begriff": "Rationalismus",       "erklaerung": "Betonung der Vernunft als Quelle sicheren Wissens." },
    { "begriff": "Realismus",           "erklaerung": "Glaube an eine von der Erkenntnis unabhängige Wirklichkeit." },
    { "begriff": "Relativismus",        "erklaerung": "Lehre, dass Wahrheiten von Standpunkt und Kultur abhängen." },
    { "begriff": "Semantik",            "erklaerung": "Lehre von Bedeutung und Sinn sprachlicher Zeichen." },
    { "begriff": "Solipsismus",         "erklaerung": "Radikaler Subjektivismus: Nur das eigene Bewusstsein ist sicher." },
    { "begriff": "Subjekt",             "erklaerung": "Erkennendes und handelndes Ich." },
    { "begriff": "Substanz",            "erklaerung": "Träger von Eigenschaften, das, was unabhängig existiert." },
    { "begriff": "Teleologie",          "erklaerung": "Lehre von Zweckursachen im Kosmos und Handeln." },
    { "begriff": "Transzendenz",        "erklaerung": "Überschreitung aller sinnlich‑empirischen Grenzen." },
    { "begriff": "Utilitarismus",       "erklaerung": "Ethik, die das größte Glück für die größte Zahl fordert." },
    { "begriff": "Wahrheit",            "erklaerung": "Übereinstimmung von Aussage und Wirklichkeit." },
    { "begriff": "Willensfreiheit",     "erklaerung": "Fähigkeit, ohne Zwang eigene Entscheidungen zu treffen." },
    { "begriff": "Wissen",              "erklaerung": "Begründete wahre Überzeugung." },
    { "begriff": "Weltanschauung",      "erklaerung": "Ganzheitliches Bild der Welt und des Lebens." },
    { "begriff": "Zweck‑Mittel-Relation", "erklaerung": "Verhältnis zwischen intendiertem Ziel und eingesetzten Mitteln." },
    { "begriff": "Äquivalenz",          "erklaerung": "Gleichwertigkeit zweier Ausdrücke oder Konzepte." },
    { "begriff": "Analytisch‑synthetischer Gegensatz", "erklaerung": "Unterscheidung zwischen begriffslogischer und erfahrungsabhängiger Aussage." },
    { "begriff": "Anthropisches Prinzip", "erklaerung": "Lehre, dass das Universum auf die Existenz von Beobachtern zugeschnitten ist." },
    { "begriff": "Ästhetische Erfahrung", "erklaerung": "Nicht‑praktische Erfahrung des Schönen." },
    { "begriff": "Autopoiesis",         "erklaerung": "Selbsterschaffungs‑ und Selbsterhaltungssysteme." },
    { "begriff": "Dasein",              "erklaerung": "Bei Heidegger: das in der Welt Seiende; Existenz." },
    { "begriff": "Effektivität",        "erklaerung": "Wirksamkeit einer Handlung oder Theorie in der Praxis." },
    { "begriff": "Emanation",           "erklaerung": "Abstufung des Seins aus einer höchsten Quelle." },
    { "begriff": "Epiphenomenalismus",  "erklaerung": "Lehre, dass geistige Zustände bloße Begleiterscheinungen physischer Prozesse sind." },
    { "begriff": "Existenzialismus",    "erklaerung": "Philosophische Bewegung, die das Individuum und seine Freiheit betont." },
    { "begriff": "Gestalt",             "erklaerung": "Ganzheitliche Struktur oder Form, die mehr ist als die Summe der Teile." },
    { "begriff": "Hylomorphismus",      "erklaerung": "Aristotelische Lehre von Form und Materie als Einheit." },
    { "begriff": "Imperativ",           "erklaerung": "Verbindliche Handlungsanweisung (z. B. Kategorischer Imperativ)." },
    { "begriff": "Kategorischer Imperativ", "erklaerung": "Kants Grundprinzip der Moral: Handle nur nach derjenigen Maxime, durch die du zugleich wollen kannst, dass sie ein allgemeines Gesetz werde." },
    { "begriff": "Logischer Positivismus","erklaerung": "Bewegung, die nur empirisch verifizierbare Aussagen als sinnhaft ansieht." },
    { "begriff": "Monade",              "erklaerung": "Leibt Leibniz: einfache, unteilbare Wesenheiten als Grundbausteine der Welt." },
    { "begriff": "Phronesis",           "erklaerung": "Aristotelische Praktische Vernunft, kluges Handeln im ethischen Kontext." },
    { "begriff": "Qualia",              "erklaerung": "Subjektive Erlebnis‑Qualität bewusster Empfindungen." },
    { "begriff": "Reifikation",         "erklaerung": "Verdinglichung abstrakter Begriffe oder sozialer Prozesse." },
    { "begriff": "Skeptizismus",        "erklaerung": "Wissenschaftlicher Zweifel an Möglichkeit sicheren Wissens." },
    { "begriff": "Subjektivität",       "erklaerung": "Persönliche Perspektive und Einzigartigkeit des Erlebens." },
    { "begriff": "Welt als Wille und Vorstellung", "erklaerung": "Schopenhauers Metaphysik, wonach die Welt zugleich Wille und Vorstellung ist." }
  ]
  